{"@context":"https://iiif.io/api/presentation/3/context.json","id":"https://canopy-iiif.github.io/example-tennessee-documentary-history/api/facet/subject/destitution.json","type":"Collection","label":{"none":["Destitution"]},"items":[{"id":"https://digital.lib.utk.edu/assemble/manifest/tdh/9209","type":"Manifest","label":{"en":["[Contract] 1827 Oct. 8, Washington county, Tennessee [with] the State of Tennessee"]},"thumbnail":[{"id":"https://digital.lib.utk.edu/collections/islandora/object/tdh%3A9209/datastream/TN","width":200,"height":200,"type":"Image","format":"image/jpeg"}],"homepage":[{"id":"https://canopy-iiif.github.io/example-tennessee-documentary-history/works/contract-1827-oct-8-washington-county-tennessee-with-the-state-of-tennessee","type":"Text","label":{"en":["[Contract] 1827 Oct. 8, Washington county, Tennessee [with] the State of Tennessee"]}}]}],"partOf":[{"id":"https://canopy-iiif.github.io/example-tennessee-documentary-history/api/facet/subject.json","type":"Collection"}],"summary":{"none":["Subject"]},"homepage":[{"id":"https://canopy-iiif.github.io/example-tennessee-documentary-history/search?subject=destitution","type":"Text","label":{"none":["Destitution"]}}]}