{"@context":"https://iiif.io/api/presentation/3/context.json","id":"https://canopy-iiif.github.io/example-tennessee-documentary-history/api/facet/subject/last-letters-before-death.json","type":"Collection","label":{"none":["Last letters before death"]},"items":[{"id":"https://digital.lib.utk.edu/assemble/manifest/tdh/6250","type":"Manifest","label":{"en":["[Letter] 1840 Aug. 12, Tyrus Springs, [Tn to] James A. Woods, Nashville, [Tn] / Robert Woods"]},"thumbnail":[{"id":"https://digital.lib.utk.edu/collections/islandora/object/tdh%3A6250/datastream/TN","width":200,"height":200,"type":"Image","format":"image/jpeg"}],"homepage":[{"id":"https://canopy-iiif.github.io/example-tennessee-documentary-history/works/letter-1840-aug-12-tyrus-springs-tn-to-james-a-woods-nashville-tn-robert-woods","type":"Text","label":{"en":["[Letter] 1840 Aug. 12, Tyrus Springs, [Tn to] James A. Woods, Nashville, [Tn] / Robert Woods"]}}]}],"partOf":[{"id":"https://canopy-iiif.github.io/example-tennessee-documentary-history/api/facet/subject.json","type":"Collection"}],"summary":{"none":["Subject"]},"homepage":[{"id":"https://canopy-iiif.github.io/example-tennessee-documentary-history/search?subject=last-letters-before-death","type":"Text","label":{"none":["Last letters before death"]}}]}