{"@context":"https://iiif.io/api/presentation/3/context.json","id":"https://canopy-iiif.github.io/example-tennessee-documentary-history/api/facet/subject/revolutionary-war-leaders.json","type":"Collection","label":{"none":["Revolutionary War leaders"]},"items":[{"id":"https://digital.lib.utk.edu/assemble/manifest/tdh/9291","type":"Manifest","label":{"en":["[Letter] 1839 May 3, Alexander, New York [to] George W. Sevier, Forest Hill, West Tennessee / Lyman C. Draper"]},"thumbnail":[{"id":"https://digital.lib.utk.edu/collections/islandora/object/tdh%3A9291/datastream/TN","width":200,"height":200,"type":"Image","format":"image/jpeg"}],"homepage":[{"id":"https://canopy-iiif.github.io/example-tennessee-documentary-history/works/letter-1839-may-3-alexander-new-york-to-george-w-sevier-forest-hill-west-tennessee-lyman-c-draper","type":"Text","label":{"en":["[Letter] 1839 May 3, Alexander, New York [to] George W. Sevier, Forest Hill, West Tennessee / Lyman C. Draper"]}}]}],"partOf":[{"id":"https://canopy-iiif.github.io/example-tennessee-documentary-history/api/facet/subject.json","type":"Collection"}],"summary":{"none":["Subject"]},"homepage":[{"id":"https://canopy-iiif.github.io/example-tennessee-documentary-history/search?subject=revolutionary-war-leaders","type":"Text","label":{"none":["Revolutionary War leaders"]}}]}