{"@context":"https://iiif.io/api/presentation/3/context.json","id":"https://canopy-iiif.github.io/example-tennessee-documentary-history/api/facet/date/april-12-1842.json","type":"Collection","label":{"none":["April 12, 1842"]},"items":[{"id":"https://digital.lib.utk.edu/assemble/manifest/tdh/1286","type":"Manifest","label":{"en":["[Claim] 1842 Apr. 12, Tahlequah District, The United States to Edward Welch"]},"thumbnail":[{"id":"https://digital.lib.utk.edu/collections/islandora/object/tdh%3A1286/datastream/TN","width":200,"height":200,"type":"Image","format":"image/jpeg"}],"homepage":[{"id":"https://canopy-iiif.github.io/example-tennessee-documentary-history/works/claim-1842-apr-12-tahlequah-district-the-united-states-to-edward-welch","type":"Text","label":{"en":["[Claim] 1842 Apr. 12, Tahlequah District, The United States to Edward Welch"]}}]}],"partOf":[{"id":"https://canopy-iiif.github.io/example-tennessee-documentary-history/api/facet/date.json","type":"Collection"}],"summary":{"none":["Date"]},"homepage":[{"id":"https://canopy-iiif.github.io/example-tennessee-documentary-history/search?date=april-12-1842","type":"Text","label":{"none":["April 12, 1842"]}}]}