{"@context":"https://iiif.io/api/presentation/3/context.json","id":"https://canopy-iiif.github.io/example-tennessee-documentary-history/api/facet/date/august-1817.json","type":"Collection","label":{"none":["August 1817"]},"items":[{"id":"https://digital.lib.utk.edu/assemble/manifest/tdh/1773","type":"Manifest","label":{"en":["Answers to enquiries relating to the Cherokees, 1817 Aug., Cherokee Agency / Colonel Return J. Meigs"]},"thumbnail":[{"id":"https://digital.lib.utk.edu/collections/islandora/object/tdh%3A1773/datastream/TN","width":200,"height":200,"type":"Image","format":"image/jpeg"}],"homepage":[{"id":"https://canopy-iiif.github.io/example-tennessee-documentary-history/works/answers-to-enquiries-relating-to-the-cherokees-1817-aug-cherokee-agency-colonel-return-j-meigs","type":"Text","label":{"en":["Answers to enquiries relating to the Cherokees, 1817 Aug., Cherokee Agency / Colonel Return J. Meigs"]}}]}],"partOf":[{"id":"https://canopy-iiif.github.io/example-tennessee-documentary-history/api/facet/date.json","type":"Collection"}],"summary":{"none":["Date"]},"homepage":[{"id":"https://canopy-iiif.github.io/example-tennessee-documentary-history/search?date=august-1817","type":"Text","label":{"none":["August 1817"]}}]}