{"@context":"https://iiif.io/api/presentation/3/context.json","id":"https://canopy-iiif.github.io/example-tennessee-documentary-history/api/facet/date/january-13-1844.json","type":"Collection","label":{"none":["January 13, 1844"]},"items":[{"id":"https://digital.lib.utk.edu/assemble/manifest/tdh/7804","type":"Manifest","label":{"en":["[Letter] 1844 Jan. 13 [to] James Jones / W. Houston"]},"thumbnail":[{"id":"https://digital.lib.utk.edu/collections/islandora/object/tdh%3A7804/datastream/TN","width":200,"height":200,"type":"Image","format":"image/jpeg"}],"homepage":[{"id":"https://canopy-iiif.github.io/example-tennessee-documentary-history/works/letter-1844-jan-13-to-james-jones-w-houston","type":"Text","label":{"en":["[Letter] 1844 Jan. 13 [to] James Jones / W. Houston"]}}]}],"partOf":[{"id":"https://canopy-iiif.github.io/example-tennessee-documentary-history/api/facet/date.json","type":"Collection"}],"summary":{"none":["Date"]},"homepage":[{"id":"https://canopy-iiif.github.io/example-tennessee-documentary-history/search?date=january-13-1844","type":"Text","label":{"none":["January 13, 1844"]}}]}