{"@context":"https://iiif.io/api/presentation/3/context.json","id":"https://canopy-iiif.github.io/example-tennessee-documentary-history/api/facet/date/july-10-1835.json","type":"Collection","label":{"none":["July 10, 1835"]},"items":[{"id":"https://digital.lib.utk.edu/assemble/manifest/tdh/1114","type":"Manifest","label":{"en":["[Letter] 1835 Jul. 10 [to] James King, Murfreesboro, Tennessee / Thomas Moore, Alexandria, Louisiana"]},"thumbnail":[{"id":"https://digital.lib.utk.edu/collections/islandora/object/tdh%3A1114/datastream/TN","width":200,"height":200,"type":"Image","format":"image/jpeg"}],"homepage":[{"id":"https://canopy-iiif.github.io/example-tennessee-documentary-history/works/letter-1835-jul-10-to-james-king-murfreesboro-tennessee-thomas-moore-alexandria-louisiana","type":"Text","label":{"en":["[Letter] 1835 Jul. 10 [to] James King, Murfreesboro, Tennessee / Thomas Moore, Alexandria, Louisiana"]}}]}],"partOf":[{"id":"https://canopy-iiif.github.io/example-tennessee-documentary-history/api/facet/date.json","type":"Collection"}],"summary":{"none":["Date"]},"homepage":[{"id":"https://canopy-iiif.github.io/example-tennessee-documentary-history/search?date=july-10-1835","type":"Text","label":{"none":["July 10, 1835"]}}]}