{"@context":"https://iiif.io/api/presentation/3/context.json","id":"https://canopy-iiif.github.io/example-tennessee-documentary-history/api/facet/date/march-4-1837.json","type":"Collection","label":{"none":["March 4, 1837"]},"items":[{"id":"https://digital.lib.utk.edu/assemble/manifest/tdh/7638","type":"Manifest","label":{"en":["1837 Mar. 1837, Lagrange, Tennessee [to] Newton Cannon, Nashville, Tennessee / John J. Potts"]},"thumbnail":[{"id":"https://digital.lib.utk.edu/collections/islandora/object/tdh%3A7638/datastream/TN","width":200,"height":200,"type":"Image","format":"image/jpeg"}],"homepage":[{"id":"https://canopy-iiif.github.io/example-tennessee-documentary-history/works/1837-mar-1837-lagrange-tennessee-to-newton-cannon-nashville-tennessee-john-j-potts","type":"Text","label":{"en":["1837 Mar. 1837, Lagrange, Tennessee [to] Newton Cannon, Nashville, Tennessee / John J. Potts"]}}]}],"partOf":[{"id":"https://canopy-iiif.github.io/example-tennessee-documentary-history/api/facet/date.json","type":"Collection"}],"summary":{"none":["Date"]},"homepage":[{"id":"https://canopy-iiif.github.io/example-tennessee-documentary-history/search?date=march-4-1837","type":"Text","label":{"none":["March 4, 1837"]}}]}