{"@context":"https://iiif.io/api/presentation/3/context.json","id":"https://canopy-iiif.github.io/example-tennessee-documentary-history/api/facet/date/march-29-1830.json","type":"Collection","label":{"none":["March 29, 1830"]},"items":[{"id":"https://digital.lib.utk.edu/assemble/manifest/tdh/9004","type":"Manifest","label":{"en":["[Commission] 1830 Mar. 29, [to] James M. Dowry / William Carroll"]},"thumbnail":[{"id":"https://digital.lib.utk.edu/collections/islandora/object/tdh%3A9004/datastream/TN","width":200,"height":200,"type":"Image","format":"image/jpeg"}],"homepage":[{"id":"https://canopy-iiif.github.io/example-tennessee-documentary-history/works/commission-1830-mar-29-to-james-m-dowry-william-carroll","type":"Text","label":{"en":["[Commission] 1830 Mar. 29, [to] James M. Dowry / William Carroll"]}}]}],"partOf":[{"id":"https://canopy-iiif.github.io/example-tennessee-documentary-history/api/facet/date.json","type":"Collection"}],"summary":{"none":["Date"]},"homepage":[{"id":"https://canopy-iiif.github.io/example-tennessee-documentary-history/search?date=march-29-1830","type":"Text","label":{"none":["March 29, 1830"]}}]}