{"@context":"https://iiif.io/api/presentation/3/context.json","id":"https://canopy-iiif.github.io/example-tennessee-documentary-history/api/facet/date/may-15-1844.json","type":"Collection","label":{"none":["May 15, 1844"]},"items":[{"id":"https://digital.lib.utk.edu/assemble/manifest/tdh/5871","type":"Manifest","label":{"en":["1844 May 15, Loudon County, Virginia [to] Andrew J. Donelson, Tennessee / John A. Carter"]},"thumbnail":[{"id":"https://digital.lib.utk.edu/collections/islandora/object/tdh%3A5871/datastream/TN","width":200,"height":200,"type":"Image","format":"image/jpeg"}],"homepage":[{"id":"https://canopy-iiif.github.io/example-tennessee-documentary-history/works/1844-may-15-loudon-county-virginia-to-andrew-j-donelson-tennessee-john-a-carter","type":"Text","label":{"en":["1844 May 15, Loudon County, Virginia [to] Andrew J. Donelson, Tennessee / John A. Carter"]}}]}],"partOf":[{"id":"https://canopy-iiif.github.io/example-tennessee-documentary-history/api/facet/date.json","type":"Collection"}],"summary":{"none":["Date"]},"homepage":[{"id":"https://canopy-iiif.github.io/example-tennessee-documentary-history/search?date=may-15-1844","type":"Text","label":{"none":["May 15, 1844"]}}]}