{"@context":"https://iiif.io/api/presentation/3/context.json","id":"https://canopy-iiif.github.io/example-tennessee-documentary-history/api/facet/date/november-6-1848.json","type":"Collection","label":{"none":["November 6, 1848"]},"items":[{"id":"https://digital.lib.utk.edu/assemble/manifest/tdh/5778","type":"Manifest","label":{"en":["1848 Nov. 6, Hartsville, T[ennessee] [to] A. Fergusson, Carthage, T[ennessee] / Lucinda Bell"]},"thumbnail":[{"id":"https://digital.lib.utk.edu/collections/islandora/object/tdh%3A5778/datastream/TN","width":200,"height":200,"type":"Image","format":"image/jpeg"}],"homepage":[{"id":"https://canopy-iiif.github.io/example-tennessee-documentary-history/works/1848-nov-6-hartsville-tennessee-to-a-fergusson-carthage-tennessee-lucinda-bell","type":"Text","label":{"en":["1848 Nov. 6, Hartsville, T[ennessee] [to] A. Fergusson, Carthage, T[ennessee] / Lucinda Bell"]}}]}],"partOf":[{"id":"https://canopy-iiif.github.io/example-tennessee-documentary-history/api/facet/date.json","type":"Collection"}],"summary":{"none":["Date"]},"homepage":[{"id":"https://canopy-iiif.github.io/example-tennessee-documentary-history/search?date=november-6-1848","type":"Text","label":{"none":["November 6, 1848"]}}]}