{"@context":"https://iiif.io/api/presentation/3/context.json","id":"https://canopy-iiif.github.io/example-tennessee-documentary-history/api/facet/place/new-jersey.json","type":"Collection","label":{"none":["New Jersey"]},"items":[{"id":"https://digital.lib.utk.edu/assemble/manifest/tdh/9248","type":"Manifest","label":{"en":["[Letter] 1838 Jan. 2, Decatur, Alabama [to] James F. Smith, Newark, New Jersey / J.J.G. Smith"]},"thumbnail":[{"id":"https://digital.lib.utk.edu/collections/islandora/object/tdh%3A9248/datastream/TN","width":200,"height":200,"type":"Image","format":"image/jpeg"}],"homepage":[{"id":"https://canopy-iiif.github.io/example-tennessee-documentary-history/works/letter-1838-jan-2-decatur-alabama-to-james-f-smith-newark-new-jersey-jjg-smith","type":"Text","label":{"en":["[Letter] 1838 Jan. 2, Decatur, Alabama [to] James F. Smith, Newark, New Jersey / J.J.G. Smith"]}}]}],"partOf":[{"id":"https://canopy-iiif.github.io/example-tennessee-documentary-history/api/facet/place.json","type":"Collection"}],"summary":{"none":["Place"]},"homepage":[{"id":"https://canopy-iiif.github.io/example-tennessee-documentary-history/search?place=new-jersey","type":"Text","label":{"none":["New Jersey"]}}]}